langtxt/__init__.py
langtxt/core/document/__init__.py
langtxt/core/document/schema.py
langtxt/core/document_loaders/__init__.py
langtxt/core/document_loaders/base.py
langtxt/core/embeddings/__init__.py
langtxt/core/embeddings/base.py
langtxt/core/text_splitters/utils.py
langtxt/core/utils/pairwise.py
langtxt/document_loaders/__init__.py
langtxt/document_loaders/directory.py
langtxt/document_loaders/docx.py
langtxt/document_loaders/html.py
langtxt/document_loaders/json.py
langtxt/document_loaders/pdf.py
langtxt/document_loaders/s3.py
langtxt/document_loaders/watson_discovery.py
langtxt/embeddings/__init__.py
langtxt/embeddings/huggingface.py
langtxt/embeddings/watsonx.py
langtxt/evaluation/__init__.py
langtxt/evaluation/knowledge_base_coverage.py
langtxt/monitor/__init__.py
langtxt/monitor/watsonx.py
langtxt/retrievers/__init__.py
langtxt/retrievers/watson_discovery.py
langtxt/text_splitters/__init__.py
langtxt/text_splitters/semantic.py
langtxt/text_splitters/sentence.py
langtxt/text_splitters/token.py
langtxt/vector_stores/__init__.py
langtxt/vector_stores/chroma.py
langtxt/vector_stores/elasticsearch.py
langtxt-0.6.0.dist-info/LICENSE
langtxt-0.6.0.dist-info/METADATA
langtxt-0.6.0.dist-info/WHEEL
langtxt-0.6.0.dist-info/RECORD
